_postgresql.abi3.so
pgserver_extend-0.0.1.dist-info/RECORD
pgserver_extend-0.0.1.dist-info/WHEEL
pgserver_extend-0.0.1.dist-info/top_level.txt
pgserver_extend-0.0.1.dist-info/METADATA
pgserver_extend-0.0.1.dist-info/licenses/LICENSE
pgserver/postgres_server.py
pgserver/__init__.py
pgserver/_build.py
pgserver/utils.py
pgserver/py.typed
pgserver/_commands.py
pgserver/.dylibs/libpq.5.dylib
pgserver/.dylibs/libecpg.6.dylib
pgserver/.dylibs/libpgtypes.3.dylib
pgserver/pginstall/bin/pg_rewind
pgserver/pginstall/bin/ecpg
pgserver/pginstall/bin/pg_basebackup
pgserver/pginstall/bin/pg_restore
pgserver/pginstall/bin/pg_isready
pgserver/pginstall/bin/createuser
pgserver/pginstall/bin/pg_config
pgserver/pginstall/bin/pg_dumpall
pgserver/pginstall/bin/pg_test_fsync
pgserver/pginstall/bin/initdb
pgserver/pginstall/bin/pg_waldump
pgserver/pginstall/bin/createdb
pgserver/pginstall/bin/reindexdb
pgserver/pginstall/bin/pg_verifybackup
pgserver/pginstall/bin/pg_receivewal
pgserver/pginstall/bin/pg_amcheck
pgserver/pginstall/bin/dropdb
pgserver/pginstall/bin/psql
pgserver/pginstall/bin/pg_checksums
pgserver/pginstall/bin/clusterdb
pgserver/pginstall/bin/postgres
pgserver/pginstall/bin/pg_archivecleanup
pgserver/pginstall/bin/dropuser
pgserver/pginstall/bin/pg_controldata
pgserver/pginstall/bin/pg_recvlogical
pgserver/pginstall/bin/pg_test_timing
pgserver/pginstall/bin/pg_upgrade
pgserver/pginstall/bin/pg_ctl
pgserver/pginstall/bin/vacuumdb
pgserver/pginstall/bin/pgbench
pgserver/pginstall/bin/pg_resetwal
pgserver/pginstall/bin/pg_dump
pgserver/pginstall/include/sqlda.h
pgserver/pginstall/include/ecpg_config.h
pgserver/pginstall/include/ecpgerrno.h
pgserver/pginstall/include/sqlda-compat.h
pgserver/pginstall/include/sql3types.h
pgserver/pginstall/include/pg_config_ext.h
pgserver/pginstall/include/pgtypes_numeric.h
pgserver/pginstall/include/postgres_ext.h
pgserver/pginstall/include/pgtypes_date.h
pgserver/pginstall/include/libpq-events.h
pgserver/pginstall/include/ecpgtype.h
pgserver/pginstall/include/pgtypes.h
pgserver/pginstall/include/pg_config_os.h
pgserver/pginstall/include/ecpglib.h
pgserver/pginstall/include/sqlda-native.h
